medcalc/__init__.py
medcalc/adjusted_body_weight.py
medcalc/albumin_corrected_anion.py
medcalc/albumin_corrected_delta_gap.py
medcalc/albumin_delta_ratio.py
medcalc/anion_gap.py
medcalc/apache_ii.py
medcalc/bmi_calculator.py
medcalc/bsa_calculator.py
medcalc/calcium_correction.py
medcalc/caprini_score.py
medcalc/cardiac_risk_index.py
medcalc/cci.py
medcalc/centor_score.py
medcalc/cha2ds2_vasc_score.py
medcalc/child_pugh_score.py
medcalc/ckd_epi_2021_creatinine.py
medcalc/compute_fena.py
medcalc/conception_date.py
medcalc/creatinine_clearance.py
medcalc/curb_65.py
medcalc/delta_gap.py
medcalc/estimated_due_date.py
medcalc/feverpain.py
medcalc/fibrosis_4.py
medcalc/framingham_risk_score.py
medcalc/free_water_deficit.py
medcalc/gestational_age.py
medcalc/glasgow_bleeding_score.py
medcalc/glasgow_coma_score.py
medcalc/has_bled_score.py
medcalc/heart_score.py
medcalc/homa_ir.py
medcalc/ideal_body_weight.py
medcalc/ldl_calculated.py
medcalc/maintenance_fluid_calc.py
medcalc/mdrd_gfr.py
medcalc/mean_arterial_pressure.py
medcalc/meldna.py
medcalc/mme.py
medcalc/perc_rule.py
medcalc/psi_score.py
medcalc/qt_calculator_bazett.py
medcalc/qt_calculator_framingham.py
medcalc/qt_calculator_fredericia.py
medcalc/qt_calculator_hodges.py
medcalc/qt_calculator_rautaharju.py
medcalc/sOsm.py
medcalc/sch.py
medcalc/sirs_criteria.py
medcalc/sofa.py
medcalc/steroid_conversion.py
medcalc/target_weight.py
medcalc/wells_criteria_dvt.py
medcalc/wells_criteria_pe.py
medcalc/utils/__init__.py
medcalc/utils/age_conversion.py
medcalc/utils/convert_temperature.py
medcalc/utils/height_conversion.py
medcalc/utils/rounding.py
medcalc/utils/unit_converter_new.py
medcalc/utils/weight_conversion.py
medcalc_bench-1.7.0.dist-info/METADATA
medcalc_bench-1.7.0.dist-info/WHEEL
medcalc_bench-1.7.0.dist-info/top_level.txt
medcalc_bench-1.7.0.dist-info/RECORD
