Metadata-Version: 2.1
Name: medcalc-bench
Version: 1.7.0
Summary: A Python package containing implementations of various medical calculators
Author-email: zikaixiao <zackzikaixiao@gmail.com>
Project-URL: Homepage, https://github.com/ncbi-nlp/MedCalc-Bench
Classifier: Programming Language :: Python :: 3
Classifier: License :: OSI Approved :: Apache Software License
Classifier: Operating System :: OS Independent
Classifier: Topic :: Scientific/Engineering :: Medical Science Apps.
Requires-Python: >=3.8
